accsr/__init__.py
accsr/config.py
accsr/conversions.py
accsr/files.py
accsr/loading.py
accsr/remote_storage.py
accsr-0.4.9.dist-info/LICENSE.md
accsr-0.4.9.dist-info/METADATA
accsr-0.4.9.dist-info/WHEEL
accsr-0.4.9.dist-info/top_level.txt
accsr-0.4.9.dist-info/RECORD
